pyposeidon/__init__.py
pyposeidon/bnd.py
pyposeidon/d3d.py
pyposeidon/dem.py
pyposeidon/grid.py
pyposeidon/jigsaw.py
pyposeidon/meteo.py
pyposeidon/misc/config_d_hydro.xml
pyposeidon/misc/critech.csv
pyposeidon/misc/default.mdf
pyposeidon/misc/ioc.csv
pyposeidon/misc/param.nml
pyposeidon/misc/param_val.nml
pyposeidon/misc/run_flow2d3d.sh
pyposeidon/model.py
pyposeidon/schism.py
pyposeidon/tide/__init__.py
pyposeidon/tide/tide.py
pyposeidon/ugmsh.py
pyposeidon/utils/__init__.py
pyposeidon/utils/bfs.py
pyposeidon/utils/cast.py
pyposeidon/utils/converter.py
pyposeidon/utils/cpoint.py
pyposeidon/utils/data.py
pyposeidon/utils/features.py
pyposeidon/utils/fix.py
pyposeidon/utils/get_value.py
pyposeidon/utils/hfun.py
pyposeidon/utils/hplot.py
pyposeidon/utils/limgrad.py
pyposeidon/utils/mplot.py
pyposeidon/utils/nest.py
pyposeidon/utils/obs.py
pyposeidon/utils/point.py
pyposeidon/utils/pos.py
pyposeidon/utils/postgrid.py
pyposeidon/utils/pplot.py
pyposeidon/utils/quads2tr.py
pyposeidon/utils/seam.py
pyposeidon/utils/sort.py
pyposeidon/utils/spline.py
pyposeidon/utils/statistics.py
pyposeidon/utils/stereo.py
pyposeidon/utils/tag.py
pyposeidon/utils/unml.py
pyposeidon/utils/verify.py
pyposeidon-0.5.2.dist-info/LICENSE
pyposeidon-0.5.2.dist-info/WHEEL
pyposeidon-0.5.2.dist-info/METADATA
pyposeidon-0.5.2.dist-info/RECORD
