Metadata-Version: 2.1
Name: pyposeidon
Version: 0.5.2
Summary: Framework for Sea Level Hydrodynamic simulations
Home-page: https://github.com/ec-jrc/pyposeidon
Keywords: Hydrodynamic,Sea,Simulation,Visualization
Author: George Breyiannis
Author-email: breyiannis@gmail.com
Requires-Python: >=3.7,<3.10
Classifier: Development Status :: 4 - Beta
Classifier: Environment :: Console
Classifier: Intended Audience :: Developers
Classifier: Intended Audience :: End Users/Desktop
Classifier: Intended Audience :: Science/Research
Classifier: License :: OSI Approved :: European Union Public Licence 1.2 (EUPL 1.2)
Classifier: Operating System :: MacOS
Classifier: Operating System :: POSIX :: Linux
Classifier: Programming Language :: Python :: 3
Classifier: Programming Language :: Python :: 3.7
Classifier: Programming Language :: Python :: 3.8
Classifier: Programming Language :: Python :: 3.9
Classifier: Topic :: Scientific/Engineering :: Atmospheric Science
Classifier: Topic :: Scientific/Engineering :: GIS
Classifier: Topic :: Scientific/Engineering :: Hydrology
Classifier: Topic :: Scientific/Engineering :: Visualization
Classifier: Topic :: Software Development :: Libraries
Requires-Dist: Cartopy (>=0.18.0,<0.19.0)
Requires-Dist: Shapely (>=1.7.1,<2.0.0)
Requires-Dist: branca (>=0.4.2,<0.5.0)
Requires-Dist: cfgrib (>=0.9.8,<0.10.0)
Requires-Dist: colorlog (>=4.7.2,<5.0.0)
Requires-Dist: dask (>=2021.2.0,<2022.0.0)
Requires-Dist: datashader (>=0.12.0,<0.13.0)
Requires-Dist: eccodes (>=1.1.0,<2.0.0)
Requires-Dist: f90nml (>=1.2,<2.0)
Requires-Dist: geopandas (>=0.8.2,<0.9.0)
Requires-Dist: geoviews (>=1.8.1,<2.0.0)
Requires-Dist: gmsh (>=4.7.1,<5.0.0)
Requires-Dist: holoviews (>=1.14.1,<2.0.0)
Requires-Dist: hvplot (>=0.7.0,<0.8.0)
Requires-Dist: ipython (>=7.20.0,<8.0.0)
Requires-Dist: llvmlite (>=0.36.0,<0.37.0)
Requires-Dist: matplotlib (>=3.3.4,<4.0.0)
Requires-Dist: moviepy (>=1.0.3,<2.0.0)
Requires-Dist: netCDF4 (>=1.5.6,<2.0.0)
Requires-Dist: numpy (>=1.20.1,<2.0.0)
Requires-Dist: panel (>=0.10.3,<0.11.0)
Requires-Dist: pygeos (>=0.9,<0.10)
Requires-Dist: pyresample (>=1.17.0,<2.0.0)
Requires-Dist: rasterio (>=1.2.0,<2.0.0)
Requires-Dist: requests (>=2.25.1,<3.0.0)
Requires-Dist: scipy (>=1.6.1,<2.0.0)
Requires-Dist: seaborn (>=0.11.1,<0.12.0)
Requires-Dist: tqdm (>=4.58.0,<5.0.0)
Requires-Dist: xarray (>=0.16.2,<0.17.0)
